Metadata-Version: 2.1
Name: cpdseqer
Version: 0.2.0
Summary: CPDseq data analysis
Home-page: https://github.com/shengqh/cpdseqer
Author: Quanhu Sheng
Author-email: quanhu.sheng.1@vumc.org
License: UNKNOWN
Download-URL: https://github.com/shengqh/cpdseqer/archive/v0.2.0.tar.gz
Platform: UNKNOWN
Classifier: Programming Language :: Python :: 3
Classifier: License :: OSI Approved :: MIT License
Classifier: Operating System :: OS Independent
